{
  "$schema": "https://json-schema.org/draft/2020-12/schema",
  "$id": "https://github.com/sonu831/digital-clone/contracts/inbound-event.schema.json",
  "title": "DigitalClone Inbound Event",
  "description": "The single normalized payload every INPUT spoke (Slack, Discord, cron, broker poller, ...) MUST emit before handing off to the AI Hub. Spokes translate provider-specific payloads INTO this shape. The Hub never sees raw provider data except via the opaque `raw` field.",
  "type": "object",
  "additionalProperties": false,
  "required": ["schema_version", "event_id", "correlation_id", "source", "type", "occurred_at"],
  "properties": {
    "schema_version": {
      "type": "string",
      "const": "1.0",
      "description": "Contract version. Bump on breaking changes; Hub may branch on it."
    },
    "event_id": {
      "type": "string",
      "format": "uuid",
      "description": "Unique id for THIS event, generated by the spoke."
    },
    "correlation_id": {
      "type": "string",
      "format": "uuid",
      "description": "Threads this event to its AI output and downstream actions. Reuse across a request lifecycle."
    },
    "source": {
      "type": "string",
      "description": "The spoke that produced the event.",
      "examples": ["slack", "discord", "telegram", "cron", "broker", "webhook"]
    },
    "type": {
      "type": "string",
      "enum": ["message", "command", "scheduled", "data_snapshot"],
      "description": "Coarse intent class. 'scheduled'/'data_snapshot' come from non-human spokes (cron, broker)."
    },
    "occurred_at": {
      "type": "string",
      "format": "date-time",
      "description": "RFC3339 timestamp of when the event happened at the source."
    },
    "actor": {
      "type": "object",
      "additionalProperties": true,
      "description": "Who triggered it (omit for machine-sourced events).",
      "properties": {
        "id": { "type": "string" },
        "display_name": { "type": "string" },
        "is_bot": { "type": "boolean" }
      }
    },
    "channel": {
      "type": "object",
      "additionalProperties": true,
      "description": "Where to reply. Maps back to a provider channel/thread.",
      "properties": {
        "id": { "type": "string" },
        "name": { "type": "string" },
        "thread_id": { "type": ["string", "null"] }
      }
    },
    "text": {
      "type": "string",
      "description": "Human-readable content / user query. Empty for pure data snapshots."
    },
    "data": {
      "type": "object",
      "additionalProperties": true,
      "description": "Structured payload for non-message events (e.g. broker P&L snapshot)."
    },
    "attachments": {
      "type": "array",
      "items": { "type": "object", "additionalProperties": true },
      "description": "Files, images, or links normalized to {type,url,name,mime}."
    },
    "raw": {
      "type": "object",
      "additionalProperties": true,
      "description": "OPAQUE original provider payload. Kept for audit/debug; the Hub MUST NOT depend on it."
    },
    "metadata": {
      "type": "object",
      "additionalProperties": true,
      "description": "Free-form spoke hints (locale, priority, etc.)."
    }
  }
}
